massdash/__init__.py
massdash/constants.py
massdash/gui.py
massdash/main.py
massdash/util.py
massdash/assets/img/MassDash_Landing_Page.png
massdash/assets/img/MassDash_Logo.ico
massdash/assets/img/MassDash_Logo_Dark.png
massdash/assets/img/MassDash_Logo_Light.png
massdash/assets/img/OpenMS.png
massdash/assets/img/tutorial/tutorial_gui_fig_1.png
massdash/assets/img/tutorial/tutorial_gui_fig_10.png
massdash/assets/img/tutorial/tutorial_gui_fig_2.png
massdash/assets/img/tutorial/tutorial_gui_fig_3.png
massdash/assets/img/tutorial/tutorial_gui_fig_4.png
massdash/assets/img/tutorial/tutorial_gui_fig_5.png
massdash/assets/img/tutorial/tutorial_gui_fig_6.png
massdash/assets/img/tutorial/tutorial_gui_fig_7.png
massdash/assets/img/tutorial/tutorial_gui_fig_7_1.png
massdash/assets/img/tutorial/tutorial_gui_fig_8.png
massdash/assets/img/tutorial/tutorial_gui_fig_9.png
massdash/assets/models/conformer/.gitkeep
massdash/dataProcessing/transformations.py
massdash/loaders/GenericChromatogramLoader.py
massdash/loaders/GenericRawDataLoader.py
massdash/loaders/GenericSpectrumLoader.py
massdash/loaders/MzMLDataLoader.py
massdash/loaders/ResultsLoader.py
massdash/loaders/SpectralLibraryLoader.py
massdash/loaders/SqMassLoader.py
massdash/loaders/__init__.py
massdash/loaders/access/GenericResultsAccess.py
massdash/loaders/access/MzMLDataAccess.py
massdash/loaders/access/OSWDataAccess.py
massdash/loaders/access/ResultsTSVDataAccess.py
massdash/loaders/access/SqMassDataAccess.py
massdash/loaders/access/TransitionPQPDataAccess.py
massdash/loaders/access/TransitionTSVDataAccess.py
massdash/loaders/access/__init__.py
massdash/peakPickers/ConformerPeakPicker.py
massdash/peakPickers/GenericPeakPicker.py
massdash/peakPickers/MRMTransitionGroupPicker.py
massdash/peakPickers/__init__.py
massdash/peakPickers/pyMRMTransitionGroupPicker.py
massdash/plotting/GenericPlotter.py
massdash/plotting/InteractivePlotter.py
massdash/plotting/InteractiveThreeDimensionPlotter.py
massdash-0.1.0.dist-info/entry_points.txt
massdash-0.1.0.dist-info/WHEEL
massdash-0.1.0.dist-info/METADATA
massdash-0.1.0.dist-info/RECORD
