Metadata-Version: 2.1
Name: massdash
Version: 0.1.0
Summary: A visualization and data exploration platform for Data-Independent Acquisition mass spectrometry data
Author-email: Justin Sing <justincsing@gmai.com>
Requires-Python: >=3.10, <=3.12
Classifier: Intended Audience :: Science/Research
Classifier: License :: OSI Approved :: BSD License
Classifier: Operating System :: OS Independent
Classifier: Programming Language :: Python :: 3.9
Classifier: Programming Language :: Python :: 3.10
Classifier: Programming Language :: Python :: 3.11
Classifier: Topic :: Scientific/Engineering :: Bio-Informatics
Classifier: Topic :: Scientific/Engineering :: Chemistry
Requires-Dist: bokeh>3.0
Requires-Dist: click>=8.1
Requires-Dist: joblib
Requires-Dist: matplotlib
Requires-Dist: numpy>=1.9.0
Requires-Dist: pandas>=0.17
Requires-Dist: plotly==5.24.1
Requires-Dist: psutil
Requires-Dist: pyopenms>=3.2.0
Requires-Dist: scipy>=1.12.0
Requires-Dist: tqdm
Requires-Dist: upsetplot
Requires-Dist: requests
Requires-Dist: pyopenms_viz
Requires-Dist: onnxruntime ; extra == "conformer"
Requires-Dist: nbsphinx ; extra == "docs"
Requires-Dist: sphinx-copybutton ; extra == "docs"
Requires-Dist: sphinx-rtd-theme ; extra == "docs"
Requires-Dist: sphinx==5.3.0 ; extra == "docs"
Requires-Dist: ipykernel ; extra == "docs"
Requires-Dist: streamlit>=1.30.0 ; extra == "gui"
Requires-Dist: streamlit-javascript ; extra == "gui"
Requires-Dist: tk ; extra == "gui"
Requires-Dist: pyautogui ; extra == "gui"
Requires-Dist: pytest ; extra == "testing"
Requires-Dist: syrupy ; extra == "testing"
Requires-Dist: tables ; extra == "testing"
Provides-Extra: conformer
Provides-Extra: docs
Provides-Extra: gui
Provides-Extra: testing
